fifo.v
module fifo #(
    parameter DEPTH = 8,  
    parameter WIDTH = 8  )(
    input  wire             clk,
    input  wire             rst,
    input  wire             wr_en,      
    input  wire             rd_en,      
    input  wire [WIDTH-1:0] data_in,   
    output reg  [WIDTH-1:0] data_out,   
    output wire             full,       
    output wire             empty   
);

  
    reg [WIDTH-1:0] mem [0:DEPTH-1];

    // Pointers
    reg [2:0] wr_ptr;   
    reg [2:0] rd_ptr;   

    // Counter 
    reg [3:0] count;   
    assign full  = (count == DEPTH);
    assign empty = (count == 0);

    always @(posedge clk or posedge rst) begin
        if (rst) begin
           
            wr_ptr   <= 0;
            rd_ptr   <= 0;
            count    <= 0;
            data_out <= 0;
        end
        else begin

           
            // Only write if write-enable is ON and FIFO is not full
            if (wr_en && !full) begin
                mem[wr_ptr] <= data_in;       // put data in the slot
                wr_ptr      <= wr_ptr + 1;    // move write pointer forward
                count       <= count + 1;     // one more item inside
            end

           
            // Only read if read-enable is ON and FIFO is not empty
            if (rd_en && !empty) begin
                data_out <= mem[rd_ptr];      // take data from the slot
                rd_ptr   <= rd_ptr + 1;       // move read pointer forward
                count    <= count - 1;        // one less item inside
            end

            // WRITE + READ at SAME TIME 
            // Count stays same
            if (wr_en && !full && rd_en && !empty) begin
                count <= count;           
            end

        end
    end

endmodule

fifotb.v
module fifo_tb;

    reg        clk, rst, wr_en, rd_en;
    reg  [7:0] data_in;
    wire [7:0] data_out;
    wire       full, empty;

    fifo #(.DEPTH(8), .WIDTH(8)) uut (
        .clk(clk), .rst(rst),
        .wr_en(wr_en), .rd_en(rd_en),
        .data_in(data_in), .data_out(data_out),
        .full(full), .empty(empty)
    );

    // Clock: flips every 5ns → 10ns period = 100MHz
    initial clk = 0;
    always #5 clk = ~clk;

    // Main 
    initial begin
        // Waveform dump (open in GTKWave to see signals)
        $dumpfile("fifo.vcd");
        $dumpvars(0, fifo_tb);

       
        rst = 1; wr_en = 0; rd_en = 0; data_in = 0;
        #20;
        rst = 0;
        #10;

        $display("--- Writing 4 values ---");
        wr_en = 1;
        data_in = 8'hAA; #10;   // write 0xAA
        data_in = 8'hBB; #10;   // write 0xBB
        data_in = 8'hCC; #10;   // write 0xCC
        data_in = 8'hDD; #10;   // write 0xDD
        wr_en = 0;
        #10;

    
        $display("--- Reading 4 values ---");
        rd_en = 1;
        #10; $display("Read: %h (expect AA)", data_out);
        #10; $display("Read: %h (expect BB)", data_out);
        #10; $display("Read: %h (expect CC)", data_out);
        #10; $display("Read: %h (expect DD)", data_out);
        rd_en = 0;
        #10;

        
        $display("--- Filling FIFO (check full flag) ---");
        wr_en = 1;
        data_in = 8'h01; #10;
        data_in = 8'h02; #10;
        data_in = 8'h03; #10;
        data_in = 8'h04; #10;
        data_in = 8'h05; #10;
        data_in = 8'h06; #10;
        data_in = 8'h07; #10;
        data_in = 8'h08; #10;
        wr_en = 0;
        $display("Full flag: %b (expect 1)", full);
        #10;

      
        $display("--- Writing when full (should be ignored) ---");
        wr_en = 1; data_in = 8'hFF; #10;
        wr_en = 0; #10;

    
        $display("--- Draining FIFO ---");
        rd_en = 1;
        repeat(8) begin
            #10; $display("Read: %h", data_out);
        end
        rd_en = 0;
        $display("Empty flag: %b (expect 1)", empty);
        #20;

        $display("--- TEST DONE ---");
        $finish;
    end

endmodule

fifo.vcd
$date
	Mon Jun 22 19:25:08 2026
$end
$version
	Icarus Verilog
$end
$timescale
	1s
$end
$scope module fifo_tb $end
$var wire 1 ! full $end
$var wire 1 " empty $end
$var wire 8 # data_out [7:0] $end
$var reg 1 $ clk $end
$var reg 8 % data_in [7:0] $end
$var reg 1 & rd_en $end
$var reg 1 ' rst $end
$var reg 1 ( wr_en $end
$scope module uut $end
$var wire 1 $ clk $end
$var wire 8 ) data_in [7:0] $end
$var wire 1 & rd_en $end
$var wire 1 ' rst $end
$var wire 1 ( wr_en $end
$var wire 1 ! full $end
$var wire 1 " empty $end
$var parameter 32 * DEPTH $end
$var parameter 32 + WIDTH $end
$var reg 4 , count [3:0] $end
$var reg 8 - data_out [7:0] $end
$var reg 3 . rd_ptr [2:0] $end
$var reg 3 / wr_ptr [2:0] $end
$upscope $end
$upscope $end
$enddefinitions $end
$comment Show the parameter values. $end
$dumpall
b1000 +
b1000 *
$end
#0
$dumpvars
b0 /
b0 .
b0 -
b0 ,
b0 )
0(
1'
0&
b0 %
0$
b0 #
1"
0!
$end
#5
1$
#10
0$
#15
1$
#20
0$
0'
#25
1$
#30
0$
b10101010 %
b10101010 )
1(
#35
0"
b1 ,
b1 /
1$
#40
0$
b10111011 %
b10111011 )
#45
b10 ,
b10 /
1$
#50
0$
b11001100 %
b11001100 )
#55
b11 ,
b11 /
1$
#60
0$
b11011101 %
b11011101 )
#65
b100 ,
b100 /
1$
#70
0$
0(
#75
1$
#80
0$
1&
#85
b11 ,
b1 .
b10101010 #
b10101010 -
1$
#90
0$
#95
b10 ,
b10 .
b10111011 #
b10111011 -
1$
#100
0$
#105
b1 ,
b11 .
b11001100 #
b11001100 -
1$
#110
0$
#115
1"
b0 ,
b100 .
b11011101 #
b11011101 -
1$
#120
0$
0&
#125
1$
#130
0$
b1 %
b1 )
1(
#135
0"
b1 ,
b101 /
1$
#140
0$
b10 %
b10 )
#145
b10 ,
b110 /
1$
#150
0$
b11 %
b11 )
#155
b11 ,
b111 /
1$
#160
0$
b100 %
b100 )
#165
b100 ,
b0 /
1$
#170
0$
b101 %
b101 )
#175
b101 ,
b1 /
1$
#180
0$
b110 %
b110 )
#185
b110 ,
b10 /
1$
#190
0$
b111 %
b111 )
#195
b111 ,
b11 /
1$
#200
0$
b1000 %
b1000 )
#205
1!
b1000 ,
b100 /
1$
#210
0$
0(
#215
1$
#220
0$
b11111111 %
b11111111 )
1(
#225
1$
#230
0$
0(
#235
1$
#240
0$
1&
#245
0!
b111 ,
b101 .
b1 #
b1 -
1$
#250
0$
#255
b110 ,
b110 .
b10 #
b10 -
1$
#260
0$
#265
b101 ,
b111 .
b11 #
b11 -
1$
#270
0$
#275
b100 ,
b0 .
b100 #
b100 -
1$
#280
0$
#285
b11 ,
b1 .
b101 #
b101 -
1$
#290
0$
#295
b10 ,
b10 .
b110 #
b110 -
1$
#300
0$
#305
b1 ,
b11 .
b111 #
b111 -
1$
#310
0$
#315
1"
b0 ,
b100 .
b1000 #
b1000 -
1$
#320
0$
0&
